tests/__init__.py
tests/conftest.py
tests/settings.py
tests/test_alternate_text.py
tests/test_auth.py
tests/test_bad_syntax.py
tests/test_caching.py
tests/test_content_name.py
tests/test_custom_filters.py
tests/test_custom_verbose_name.py
tests/test_html.py
tests/test_models.py
tests/test_simple.py
tests/urls.py
tests/utils.py
tests/filters/__init__.py
tests/filters/test_markdown.py
tests/filters/test_uploaded_file.py
tinycontent/__init__.py
tinycontent/admin.py
tinycontent/apps.py
tinycontent/conf.py
tinycontent/models.py
tinycontent/filters/__init__.py
tinycontent/filters/builtin.py
tinycontent/filters/md.py
tinycontent/migrations/0001_initial.py
tinycontent/migrations/0002_tinycontentfileupload.py
tinycontent/migrations/0003_update_slug.py
tinycontent/migrations/0004_py3_compatible.py
tinycontent/migrations/__init__.py
tinycontent/templates/tinycontent/tinycontent.html
tinycontent/templates/tinycontent/tinycontent_add.html
tinycontent/templatetags/__init__.py
tinycontent/templatetags/tinycontent_tags.py
tinycontent/utils/__init__.py
tinycontent/utils/file_uploads.py
tinycontent/utils/importer.py
django_tinycontent-0.9.0.dist-info/LICENSE
django_tinycontent-0.9.0.dist-info/METADATA
django_tinycontent-0.9.0.dist-info/WHEEL
django_tinycontent-0.9.0.dist-info/top_level.txt
django_tinycontent-0.9.0.dist-info/RECORD
