Metadata-Version: 2.1
Name: django-tinycontent
Version: 0.9.0
Summary: A Django app for managing re-usable blocks of tiny content.
Home-page: http://github.com/dominicrodger/django-tinycontent
Author: Dominic Rodger
Author-email: internet@dominicrodger.com
License: BSD
Platform: UNKNOWN
Classifier: Development Status :: 5 - Production/Stable
Classifier: Framework :: Django
Classifier: License :: OSI Approved :: BSD License
Classifier: Environment :: Web Environment
Classifier: Intended Audience :: Developers
Classifier: Operating System :: OS Independent
Classifier: Programming Language :: Python :: 2.7
Classifier: Programming Language :: Python :: 3.5
License-File: LICENSE
Requires-Dist: Django (>=2.0)
Requires-Dist: django-autoslug (>=1.8.0)
Requires-Dist: markdown
